odoo/addons/sale_expense_manual_reinvoice/README.rst
odoo/addons/sale_expense_manual_reinvoice/__init__.py
odoo/addons/sale_expense_manual_reinvoice/__manifest__.py
odoo/addons/sale_expense_manual_reinvoice/i18n/es.po
odoo/addons/sale_expense_manual_reinvoice/i18n/it.po
odoo/addons/sale_expense_manual_reinvoice/i18n/sale_expense_manual_reinvoice.pot
odoo/addons/sale_expense_manual_reinvoice/models/__init__.py
odoo/addons/sale_expense_manual_reinvoice/models/account_analytic_line.py
odoo/addons/sale_expense_manual_reinvoice/models/account_move_line.py
odoo/addons/sale_expense_manual_reinvoice/models/hr_expense.py
odoo/addons/sale_expense_manual_reinvoice/models/product_template.py
odoo/addons/sale_expense_manual_reinvoice/readme/CONFIGURE.rst
odoo/addons/sale_expense_manual_reinvoice/readme/CONTRIBUTORS.rst
odoo/addons/sale_expense_manual_reinvoice/readme/DESCRIPTION.rst
odoo/addons/sale_expense_manual_reinvoice/readme/ROADMAP.rst
odoo/addons/sale_expense_manual_reinvoice/readme/USAGE.rst
odoo/addons/sale_expense_manual_reinvoice/static/description/configure.png
odoo/addons/sale_expense_manual_reinvoice/static/description/icon.png
odoo/addons/sale_expense_manual_reinvoice/static/description/index.html
odoo/addons/sale_expense_manual_reinvoice/static/description/reinvoice.png
odoo/addons/sale_expense_manual_reinvoice/tests/__init__.py
odoo/addons/sale_expense_manual_reinvoice/tests/test_sale_expense_manual_reinvoice.py
odoo/addons/sale_expense_manual_reinvoice/views/account_analytic_line.xml
odoo/addons/sale_expense_manual_reinvoice/views/hr_expense.xml
odoo/addons/sale_expense_manual_reinvoice/views/product_template.xml
odoo_addon_sale_expense_manual_reinvoice-15.0.1.0.1.7.dist-info/METADATA
odoo_addon_sale_expense_manual_reinvoice-15.0.1.0.1.7.dist-info/WHEEL
odoo_addon_sale_expense_manual_reinvoice-15.0.1.0.1.7.dist-info/top_level.txt
odoo_addon_sale_expense_manual_reinvoice-15.0.1.0.1.7.dist-info/RECORD
